byted_assert_std_executor/__init__.py
byted_assert_std_executor-0.0.1.dist-info/METADATA
byted_assert_std_executor-0.0.1.dist-info/WHEEL
byted_assert_std_executor-0.0.1.dist-info/top_level.txt
byted_assert_std_executor-0.0.1.dist-info/RECORD
