Metadata-Version: 2.1
Name: byted-assert-std-executor
Version: 0.0.1
Summary: A simple package named byted_assert_std_executor
Home-page: https://github.com/artifact/byted_assert_std_executor.git
Author: artifact
Author-email: artifact@example.com
License: UNKNOWN
Platform: UNKNOWN
Classifier: Programming Language :: Python :: 3
Classifier: License :: OSI Approved :: MIT License
Classifier: Operating System :: OS Independent
